tonyfast/__init__.py
tonyfast/articles.ipynb
tonyfast/articles.md
tonyfast/ainteractive/__init__.py
tonyfast/ainteractive/autointeractive.ipynb
tonyfast/ainteractive/autointeractive.md
tonyfast/ainteractive/test_autointeractive.ipynb
tonyfast/ainteractive/test_autointeractive.md
tonyfast/configfile/2019-10-29-anyconfig-first-look.ipynb
tonyfast/configfile/2019-10-29-anyconfig-first-look.md
tonyfast/essays/calligrams/2019-11-05-calligrams.ipynb
tonyfast/essays/calligrams/2019-11-05-calligrams.md
tonyfast/first_look/anyconfig/2019-10-29-anyconfig-first-look.ipynb
tonyfast/first_look/anyconfig/2019-10-29-anyconfig-first-look.md
tonyfast/first_look/dask_pub_sub/2019-11-02-dask-pub-sub-actor.ipynb
tonyfast/first_look/dask_pub_sub/2019-11-02-dask-pub-sub-actor.md
tonyfast/first_look/github_api_boiler/2019-10-29-head-first-into-github.ipynb
tonyfast/first_look/github_api_boiler/2019-10-29-head-first-into-github.md
tonyfast/first_look/profilers/2019-10-28-snakeviz-pyspy-profiling.ipynb
tonyfast/first_look/profilers/2019-10-28-snakeviz-pyspy-profiling.md
tonyfast/gidget/__init__.py
tonyfast/gidget/await-gidgethub.ipynb
tonyfast/gidget/await-gidgethub.md
tonyfast/github-api/2019-10-13-github-stats-api.ipynb
tonyfast/github-api/2019-10-13-github-stats-api.md
tonyfast/github-api/2019-10-14-quansight-events.ipynb
tonyfast/github-api/2019-10-14-quansight-events.md
tonyfast/jschema/__init__.py
tonyfast/jschema/jschema.ipynb
tonyfast/jschema/jschema.md
tonyfast/literacy/2019-10-04-doctest-post-run-cell.ipynb
tonyfast/literacy/2019-10-04-doctest-post-run-cell.md
tonyfast/literacy/2019-10-05-Inline-code.ipynb
tonyfast/literacy/2019-10-05-Inline-code.md
tonyfast/literacy/2019-10-05-interactive-jinja-templates.ipynb
tonyfast/literacy/2019-10-05-interactive-jinja-templates.md
tonyfast/literacy/2019-10-08-xonsh-compiler.ipynb
tonyfast/literacy/2019-10-08-xonsh-compiler.md
tonyfast/literacy/2019-10-11-literate-computing-documents.ipynb
tonyfast-2019.11.25.18.20.dist-info/METADATA
tonyfast-2019.11.25.18.20.dist-info/WHEEL
tonyfast-2019.11.25.18.20.dist-info/entry_points.txt
tonyfast-2019.11.25.18.20.dist-info/top_level.txt
tonyfast-2019.11.25.18.20.dist-info/RECORD
